MANIFEST.in
README.md
setup.py
compresshtml/__init__.py
compresshtml/compresshtml.py
compresshtml/decorators.py
compresshtml/middleware.py
django_compresshtml.egg-info/PKG-INFO
django_compresshtml.egg-info/SOURCES.txt
django_compresshtml.egg-info/dependency_links.txt
django_compresshtml.egg-info/requires.txt
django_compresshtml.egg-info/top_level.txt