Metadata-Version: 1.0
Name: django-compresshtml
Version: 0.1.1
Summary: HTML compressor for django
Home-page: UNKNOWN
Author: kamagatos
Author-email: kamagatos@gmail.com
License: UNKNOWN
Platform: UNKNOWN
